mivia/__init__.py
mivia/client.py
mivia/exceptions.py
mivia/models.py
mivia/sync_client.py
mivia/cli/__init__.py
mivia/cli/main.py
mivia-0.1.3.dist-info/METADATA
mivia-0.1.3.dist-info/WHEEL
mivia-0.1.3.dist-info/entry_points.txt
mivia-0.1.3.dist-info/licenses/LICENSE
mivia-0.1.3.dist-info/RECORD
