Metadata-Version: 2.4
Name: mivia
Version: 0.1.3
Summary: Python API client for MiViA (Microstructure Analysis)
Project-URL: Homepage, https://mivia.ai
Project-URL: Documentation, https://github.com/MiViA-GmbH/mivia-api-py#readme
Project-URL: Repository, https://github.com/MiViA-GmbH/mivia-api-py
Project-URL: Issues, https://github.com/MiViA-GmbH/mivia-api-py/issues
Author-email: Krzysztof Bzowski <krzysztof.bzowski@mivia.ai>
License: MIT
License-File: LICENSE
Keywords: analysis,api,client,microscopy,microstructure,mivia
Classifier: Development Status :: 4 - Beta
Classifier: Intended Audience :: Developers
Classifier: Intended Audience :: Science/Research
Classifier: License :: OSI Approved :: MIT License
Classifier: Operating System :: OS Independent
Classifier: Programming Language :: Python :: 3
Classifier: Programming Language :: Python :: 3.11
Classifier: Programming Language :: Python :: 3.12
Classifier: Programming Language :: Python :: 3.13
Classifier: Topic :: Scientific/Engineering :: Image Processing
Classifier: Typing :: Typed
Requires-Python: >=3.11
Requires-Dist: httpx>=0.27.0
Requires-Dist: pydantic-settings>=2.0.0
Requires-Dist: pydantic>=2.0.0
Requires-Dist: rich>=13.0.0
Requires-Dist: typer>=0.12.0
Provides-Extra: dev
Requires-Dist: lefthook>=1.10.0; extra == 'dev'
Requires-Dist: mypy>=1.10.0; extra == 'dev'
Requires-Dist: pytest-asyncio>=0.23.0; extra == 'dev'
Requires-Dist: pytest-httpx>=0.30.0; extra == 'dev'
Requires-Dist: pytest>=8.0.0; extra == 'dev'
Requires-Dist: ruff>=0.4.0; extra == 'dev'
